ups_locator/__init__.py
ups_locator/sdk.py
ups_locator/hooks/__init__.py
ups_locator/hooks/hook.py
ups_locator/models/__init__.py
ups_locator/models/access_point_information_access_point_status.py
ups_locator/models/access_point_information_availability.py
ups_locator/models/access_point_information_business_classification_list.py
ups_locator/models/access_point_information_private_network_list.py
ups_locator/models/access_point_search_exclude_from_result.py
ups_locator/models/access_point_search_include_criteria.py
ups_locator/models/additional_comments_comment_type.py
ups_locator/models/availability_dcr_availability.py
ups_locator/models/availability_shipping_availability.py
ups_locator/models/available_location_attributes_option_code.py
ups_locator/models/available_location_attributes_option_code_transportation_pick_up_schedule.py
ups_locator/models/available_location_attributes_option_type.py
ups_locator/models/available_location_attributes_pick_up_pick_up_details.py
ups_locator/models/available_location_attributes_transportation_pick_up_schedule_pick_up.py
ups_locator/models/base.py
ups_locator/models/business_classification_list_business_classification.py
ups_locator/models/dcr_availability_unavailable_reason.py
ups_locator/models/distance_unit_of_measurement.py
ups_locator/models/drop_location_access_point_information.py
ups_locator/models/drop_location_additional_comments.py
ups_locator/models/drop_location_address_key_format.py
ups_locator/models/drop_location_distance.py
ups_locator/models/drop_location_geocode.py
ups_locator/models/drop_location_ivr.py
ups_locator/models/drop_location_localized_instruction.py
ups_locator/models/drop_location_location_attribute.py
ups_locator/models/drop_location_location_image.py
ups_locator/models/drop_location_operating_hours.py
ups_locator/models/drop_location_promotion_information.py
ups_locator/models/drop_location_service_offering_list.py
ups_locator/models/drop_location_sort_code.py
ups_locator_client-1.0.0.dist-info/LICENSE
ups_locator_client-1.0.0.dist-info/METADATA
ups_locator_client-1.0.0.dist-info/WHEEL
ups_locator_client-1.0.0.dist-info/top_level.txt
ups_locator_client-1.0.0.dist-info/RECORD
