Metadata-Version: 2.1
Name: ups-locator-client
Version: 1.0.0
Summary: Search for UPS shipping locations based on type and available services. In order to obtain your bearer token please follow the instructions at https://developer.ups.com/get-started, or use the UPS Authorization API. 
License: MIT
Requires-Python: >=3.7
License-File: LICENSE
Requires-Dist: requests >=2.31.0
